docs/README.md
docs/api-reference.md
docs/changelog.md
docs/configuration.md
docs/contributing.md
docs/examples.md
docs/installation.md
docs/quick-start.md
docs/troubleshooting.md
examples/advanced_usage.py
examples/async_tasks.py
examples/basic_usage.py
examples/config_file_example.py
examples/cron_examples.py
examples/error_handling.py
examples/scheduler_config.yaml
examples/simple_demo.py
pyscheduler/__init__.py
pyscheduler/cli/__init__.py
pyscheduler/cli/main.py
pyscheduler/config/__init__.py
pyscheduler/config/decorators.py
pyscheduler/config/manager.py
pyscheduler/core/__init__.py
pyscheduler/core/executors.py
pyscheduler/core/scheduler.py
pyscheduler/core/task.py
pyscheduler/core/triggers.py
pyscheduler/utils/__init__.py
pyscheduler/utils/exceptions.py
pyscheduler/utils/helpers.py
pyscheduler/utils/logger.py
pyscheduler_fox-1.0.0.dist-info/licenses/LICENSE
pyscheduler_fox-1.0.0.dist-info/METADATA
pyscheduler_fox-1.0.0.dist-info/WHEEL
pyscheduler_fox-1.0.0.dist-info/top_level.txt
pyscheduler_fox-1.0.0.dist-info/RECORD
