Metadata-Version: 2.4
Name: pyscheduler-fox
Version: 1.0.0
Summary: A powerful yet simple Python task scheduler
Home-page: https://github.com/Tiger-Foxx/PyScheduler
Author: Fox
Author-email: Fox <donfackarthur750@gmail.com>
License: MIT
Project-URL: Homepage, https://github.com/Tiger-Foxx/PyScheduler
Project-URL: Documentation, https://github.com/Tiger-Foxx/PyScheduler/blob/main/docs/
Project-URL: Repository, https://github.com/Tiger-Foxx/PyScheduler
Project-URL: Issues, https://github.com/Tiger-Foxx/PyScheduler/issues
Project-URL: Changelog, https://github.com/Tiger-Foxx/PyScheduler/blob/main/docs/changelog.md
Project-URL: Examples, https://github.com/Tiger-Foxx/PyScheduler/tree/main/examples
Keywords: scheduler,task,cron,async,threading,automation,jobs,background,periodic,interval,daemon,service
Classifier: Development Status :: 5 - Production/Stable
Classifier: Intended Audience :: Developers
Classifier: Intended Audience :: System Administrators
Classifier: License :: OSI Approved :: MIT License
Classifier: Operating System :: OS Independent
Classifier: Programming Language :: Python :: 3
Classifier: Programming Language :: Python :: 3.7
Classifier: Programming Language :: Python :: 3.8
Classifier: Programming Language :: Python :: 3.9
Classifier: Programming Language :: Python :: 3.10
Classifier: Programming Language :: Python :: 3.11
Classifier: Programming Language :: Python :: 3.12
Classifier: Programming Language :: Python :: 3.13
Classifier: Topic :: Software Development :: Libraries :: Python Modules
Classifier: Topic :: System :: Monitoring
Classifier: Topic :: System :: Systems Administration
Classifier: Topic :: Utilities
Classifier: Environment :: Console
Classifier: Framework :: AsyncIO
Requires-Python: >=3.7
License-File: LICENSE
Provides-Extra: full
Requires-Dist: pyyaml>=5.1.0; extra == "full"
Requires-Dist: pytz>=2021.1; extra == "full"
Requires-Dist: croniter>=1.0.0; extra == "full"
Provides-Extra: yaml
Requires-Dist: pyyaml>=5.1.0; extra == "yaml"
Provides-Extra: timezone
Requires-Dist: pytz>=2021.1; extra == "timezone"
Provides-Extra: cron
Requires-Dist: croniter>=1.0.0; extra == "cron"
Provides-Extra: dev
Requires-Dist: pytest>=7.0.0; extra == "dev"
Requires-Dist: pytest-cov>=4.0.0; extra == "dev"
Requires-Dist: pytest-asyncio>=0.20.0; extra == "dev"
Requires-Dist: black>=22.0.0; extra == "dev"
Requires-Dist: flake8>=5.0.0; extra == "dev"
Requires-Dist: mypy>=1.0.0; extra == "dev"
Requires-Dist: build>=0.8.0; extra == "dev"
Requires-Dist: twine>=4.0.0; extra == "dev"
Dynamic: author
Dynamic: home-page
Dynamic: license-file
Dynamic: requires-python
